koverj/__init__.py
koverj/agent/__init__.py
koverj/agent/koverj_selene_listener.py
koverj/agent/selenium/__init__.py
koverj/agent/selenium/locator_watching_driver.py
koverj/agent/selenium/webdriver_locator_listener.py
koverj/agent/selenium_agent.py
koverj/common/__init__.py
koverj/common/client/__init__.py
koverj/common/client/koverj_client.py
koverj/common/client/locators_life_cycle.py
koverj/common/config/__init__.py
koverj/common/config/env.cfg
koverj/common/config/project_config.py
koverj/common/model/__init__.py
koverj/common/model/locator.py
koverj/common/model/test_result.py
koverj/common/plugin/__init__.py
koverj/common/plugin/pytest_koverj_plugin.py
koverj/common/service/__init__.py
koverj/common/service/koverj_service.py
koverj/koverj-browser-plugin/.gitignore
koverj/koverj-browser-plugin/assets/css/bootstrap.min.css
koverj/koverj-browser-plugin/assets/css/koverj.css
koverj/koverj-browser-plugin/assets/css/plugin.css
koverj/koverj-browser-plugin/assets/icon.png
koverj/koverj-browser-plugin/assets/js/jquery-3.3.1.js
koverj/koverj-browser-plugin/assets/js/jquery.sidebar.min.js
koverj/koverj-browser-plugin/assets/js/notify.min.js
koverj/koverj-browser-plugin/assets/js/vis-network.min.js
koverj/koverj-browser-plugin/graph.html
koverj/koverj-browser-plugin/index.html
koverj/koverj-browser-plugin/manifest.json
koverj/koverj-browser-plugin/mock/index.js
koverj/koverj-browser-plugin/mock/locators.json
koverj/koverj-browser-plugin/mock/locators2.json
koverj/koverj-browser-plugin/mock/package.json
koverj/koverj-browser-plugin/options.html
koverj/koverj-browser-plugin/plugin/background.js
koverj/koverj-browser-plugin/plugin/content.js
koverj/koverj-browser-plugin/plugin/graph.js
koverj/koverj-browser-plugin/plugin/options.js
koverj/koverj-browser-plugin/plugin/plugin.js
koverj-0.1.105.dist-info/WHEEL
koverj-0.1.105.dist-info/METADATA
koverj-0.1.105.dist-info/RECORD
