Metadata-Version: 2.1
Name: koverj
Version: 0.1.105
Summary: Test coverage for selenium based tests
Home-page: https://github.com/Igur007/koverj-py
License: MIT
Author: Ivan Huryn
Author-email: igur007@gmail.com
Requires-Python: >=3.7,<4.0
Classifier: License :: OSI Approved :: MIT License
Classifier: Programming Language :: Python :: 3
Classifier: Programming Language :: Python :: 3.7
Classifier: Programming Language :: Python :: 3.8
Requires-Dist: configparser (>=5.0.0,<6.0.0)
Requires-Dist: future (>=0.18.2,<0.19.0)
Requires-Dist: pytest
Requires-Dist: requests (>=2.23.0,<3.0.0)
Requires-Dist: selene (>=1.0.0a13,<2.0.0)
Requires-Dist: selenium (==3.141)
Requires-Dist: uplink (>=0.9.1,<0.10.0)
Project-URL: Repository, https://github.com/Igur007/koverj-py
